scholarimpact/__init__.py
scholarimpact/_version.py
scholarimpact/assets/README.md
scholarimpact/assets/__init__.py
scholarimpact/assets/fonts/OFL-SpaceGrotesk.txt
scholarimpact/assets/fonts/OFL-SpaceMono.txt
scholarimpact/assets/fonts/SpaceGrotesk-SemiBold.ttf
scholarimpact/assets/fonts/SpaceGrotesk-VariableFont_wght.ttf
scholarimpact/assets/fonts/SpaceMono-Bold.ttf
scholarimpact/assets/fonts/SpaceMono-BoldItalic.ttf
scholarimpact/assets/fonts/SpaceMono-Italic.ttf
scholarimpact/assets/fonts/SpaceMono-Regular.ttf
scholarimpact/assets/streamlit/config.toml
scholarimpact/cli/__init__.py
scholarimpact/cli/main.py
scholarimpact/cli/commands/__init__.py
scholarimpact/cli/commands/crawl.py
scholarimpact/cli/commands/dashboard.py
scholarimpact/cli/commands/extract.py
scholarimpact/cli/commands/generate.py
scholarimpact/core/__init__.py
scholarimpact/core/crawler.py
scholarimpact/core/extractor.py
scholarimpact/core/utils.py
scholarimpact/dashboard/__init__.py
scholarimpact/dashboard/app.py
scholarimpact/dashboard/components/__init__.py
scholarimpact/dashboard/components/base.py
scholarimpact/dashboard/components/config.py
scholarimpact/dashboard/components/layout.py
scholarimpact/dashboard/components/streamlit_app.py
scholarimpact/data/__init__.py
scholarimpact/data/loader.py
scholarimpact-0.0.6.dist-info/licenses/LICENSE
scholarimpact-0.0.6.dist-info/METADATA
scholarimpact-0.0.6.dist-info/WHEEL
scholarimpact-0.0.6.dist-info/entry_points.txt
scholarimpact-0.0.6.dist-info/top_level.txt
scholarimpact-0.0.6.dist-info/RECORD
