Metadata-Version: 2.4
Name: scholarimpact
Version: 0.0.6
Summary: A bibliometric tool to analyse, visualise, and share your research impact, output and scholarly influence using Google Scholar and OpenAlex data
Author-email: Abhishek Tiwari <scholarimpact@abhishek-tiwari.com>
License: MIT
Project-URL: Homepage, https://github.com/abhishektiwari/scholarimpact
Project-URL: Repository, https://github.com/abhishektiwari/scholarimpact.git
Project-URL: Issues, https://github.com/abhishektiwari/scholarimpact/issues
Keywords: citations,google-scholar,research,dashboard,analysis,academic
Classifier: Development Status :: 3 - Alpha
Classifier: Intended Audience :: Science/Research
Classifier: License :: OSI Approved :: MIT License
Classifier: Programming Language :: Python :: 3
Classifier: Programming Language :: Python :: 3.9
Classifier: Programming Language :: Python :: 3.10
Classifier: Programming Language :: Python :: 3.11
Classifier: Programming Language :: Python :: 3.12
Classifier: Programming Language :: Python :: 3.13
Classifier: Topic :: Scientific/Engineering :: Information Analysis
Classifier: Topic :: Internet :: WWW/HTTP :: Dynamic Content
Requires-Python: >=3.9
License-File: LICENSE
Requires-Dist: streamlit>=1.28.0
Requires-Dist: pandas>=2.0.0
Requires-Dist: numpy>=1.24.0
Requires-Dist: plotly>=5.14.0
Requires-Dist: click>=8.0.0
Requires-Dist: PyYAML>=6.0
Requires-Dist: requests>=2.28.0
Requires-Dist: beautifulsoup4>=4.11.0
Requires-Dist: selenium>=4.10.0
Requires-Dist: scholarly>=1.7.11
Requires-Dist: pyalex>=0.18
Requires-Dist: pycountry>=22.0.0
Requires-Dist: geopy>=2.4.1
Requires-Dist: tqdm>=4.65.0
Provides-Extra: dev
Requires-Dist: pytest>=7.0.0; extra == "dev"
Requires-Dist: pytest-cov>=4.0.0; extra == "dev"
Requires-Dist: black>=23.0.0; extra == "dev"
Requires-Dist: isort>=5.12.0; extra == "dev"
Requires-Dist: flake8>=6.0.0; extra == "dev"
Provides-Extra: build
Requires-Dist: build>=0.8.0; extra == "build"
Requires-Dist: twine>=4.0.0; extra == "build"
Requires-Dist: setuptools-scm>=6.2.0; extra == "build"
Dynamic: license-file
